hltv_api/__init__.py
hltv_api/client.py
hltv_api-0.1.1.dist-info/WHEEL
hltv_api-0.1.1.dist-info/METADATA
hltv_api-0.1.1.dist-info/RECORD
