Metadata-Version: 2.1
Name: hltv-api
Version: 0.1.1
Summary: An unofficial async HLTV client
Author: Daniel van Flymen
Author-email: vanflymen@gmail.com
Requires-Python: >=3.8,<4.0
Classifier: Programming Language :: Python :: 3
Classifier: Programming Language :: Python :: 3.8
Classifier: Programming Language :: Python :: 3.9
Requires-Dist: aiohttp (>=3.7.4,<4.0.0)
Requires-Dist: beautifulsoup4 (>=4.9.3,<5.0.0)
Requires-Dist: lxml (>=4.6.2,<5.0.0)
Requires-Dist: pytz (>=2021.1,<2022.0)
